{
  "xgboost_version": "3.2.0",
  "gpu_device_ordinal": 0,
  "meter_id": 2,
  "meter_name": "steam",
  "data_root": "F:\\Desktop\\Final\\USTB-graduation-project\\ASHRAE-Great Energy Predictor III\\ashrae-energy-prediction",
  "train_data_path": "F:\\Desktop\\Final\\workspace\\preprocessed_data\\meter_2\\log1p_minmax_train.csv",
  "valid_data_path": "F:\\Desktop\\Final\\workspace\\preprocessed_data\\meter_2\\log1p_minmax_valid.csv",
  "test_data_path": "F:\\Desktop\\Final\\workspace\\preprocessed_data\\meter_2\\log1p_minmax_test.csv",
  "preprocessing_summary_path": "F:\\Desktop\\Final\\workspace\\preprocessed_data\\meter_2\\log1p_minmax_summary.json",
  "output_dir": "F:\\Desktop\\Final\\workspace\\XGBoost\\xgboost_other_meters_log1p-minmax_outputs\\meter_2",
  "preprocessed_data_dir": "F:\\Desktop\\Final\\workspace\\preprocessed_data\\meter_2",
  "target_preprocess": "log1p_then_train_minmax",
  "target_log1p_min": 0.0,
  "target_log1p_max": 16.902212142944336,
  "train_ratio": 0.8,
  "valid_ratio": 0.1,
  "test_ratio": 0.1,
  "feature_count": 34,
  "xgboost_feature_cols": [
    "building_id",
    "meter",
    "site_id",
    "primary_use",
    "square_feet",
    "year_built",
    "floor_count",
    "air_temperature",
    "cloud_coverage",
    "dew_temperature",
    "precip_depth_1_hr",
    "sea_level_pressure",
    "wind_direction",
    "wind_speed",
    "age",
    "beaufort_scale",
    "month_datetime",
    "weekofyear_datetime",
    "dayofyear_datetime",
    "hour_datetime",
    "day_week",
    "day_month_datetime",
    "week_month_datetime",
    "age_missing",
    "air_temperature_missing",
    "beaufort_scale_missing",
    "cloud_coverage_missing",
    "dew_temperature_missing",
    "floor_count_missing",
    "precip_depth_1_hr_missing",
    "sea_level_pressure_missing",
    "wind_direction_missing",
    "wind_speed_missing",
    "year_built_missing"
  ],
  "categorical_features": [
    "site_id",
    "building_id",
    "primary_use",
    "meter",
    "wind_direction",
    "beaufort_scale",
    "month_datetime",
    "weekofyear_datetime",
    "hour_datetime",
    "day_week",
    "day_month_datetime",
    "week_month_datetime"
  ],
  "numerical_features": [
    "square_feet",
    "year_built",
    "age",
    "air_temperature",
    "cloud_coverage",
    "dew_temperature",
    "precip_depth_1_hr",
    "floor_count",
    "dayofyear_datetime"
  ],
  "train_row_count": 2075012,
  "valid_row_count": 271599,
  "test_row_count": 265556,
  "splits": [
    {
      "split": "train",
      "start_timestamp": "2016-01-01 00:00:00",
      "end_timestamp": "2016-10-19 18:00:00",
      "row_count": 2075012
    },
    {
      "split": "valid",
      "start_timestamp": "2016-10-19 19:00:00",
      "end_timestamp": "2016-11-25 09:00:00",
      "row_count": 271599
    },
    {
      "split": "test",
      "start_timestamp": "2016-11-25 10:00:00",
      "end_timestamp": "2016-12-31 23:00:00",
      "row_count": 265556
    }
  ],
  "validation_mse": 0.00882455799728632,
  "validation_mae": 0.06893771141767502,
  "validation_r2": 0.5498031377792358,
  "validation_smape": 38.09171676635742,
  "validation_rmse": 0.0939391185677528,
  "test_mse": 0.008801105432212353,
  "test_mae": 0.07158425450325012,
  "test_r2": 0.4681739807128906,
  "test_smape": 30.45722198486328,
  "test_rmse": 0.09381420698493567,
  "best_iteration_round_count": 64,
  "model_path": "F:\\Desktop\\Final\\workspace\\XGBoost\\xgboost_other_meters_log1p-minmax_outputs\\meter_2\\xgboost_final_model.json",
  "model_params_path": "F:\\Desktop\\Final\\workspace\\XGBoost\\xgboost_other_meters_log1p-minmax_outputs\\meter_2\\xgboost_model_params.json",
  "validation_metrics_path": "F:\\Desktop\\Final\\workspace\\XGBoost\\xgboost_other_meters_log1p-minmax_outputs\\meter_2\\xgboost_validation_metrics.json",
  "test_metrics_path": "F:\\Desktop\\Final\\workspace\\XGBoost\\xgboost_other_meters_log1p-minmax_outputs\\meter_2\\xgboost_test_metrics.json",
  "importance_path": "F:\\Desktop\\Final\\workspace\\XGBoost\\xgboost_other_meters_log1p-minmax_outputs\\meter_2\\xgboost_feature_importance.csv",
  "split_summary_path": "F:\\Desktop\\Final\\workspace\\XGBoost\\xgboost_other_meters_log1p-minmax_outputs\\meter_2\\xgboost_time_series_split.csv"
}